zobepy/__init__.py
zobepy/binary_size_formatter.py
zobepy/dump.py
zobepy/subpr.py
zobepy/util.py
zobepy-1.0.4.dist-info/METADATA
zobepy-1.0.4.dist-info/WHEEL
zobepy-1.0.4.dist-info/top_level.txt
zobepy-1.0.4.dist-info/RECORD
